package_simple/__init__.py
package_simple/file1_name.py
package_simple/file2_name.py
package_simple-0.0.1.dist-info/METADATA
package_simple-0.0.1.dist-info/WHEEL
package_simple-0.0.1.dist-info/top_level.txt
package_simple-0.0.1.dist-info/RECORD
