Metadata-Version: 2.1
Name: package-simple
Version: 0.0.1
Summary: Example of package creation
Home-page: https://github.com/rosacarla/simple-package-template
Author: Carla Edila
Author-email: rosa.carla@pucpr.edu.br
License: UNKNOWN
Platform: UNKNOWN
Requires-Python: >=3.8
